[
	{
		"id": 1,
		"category": "test",
		"content": "ニホンウナギの産卵場所はどこ？",
		"option_type": "text",
		"options": [
			{
				"content": "川",
				"accuracy": 0.5
			}
		],
		"answer": {
			"content": "海嶺",
			"explanation": "ニホンウナギはマリアナ海嶺で産卵します。"
		}
	},
	{
		"id": 2,
		"category": "test",
		"content": "ウナギの寿命は平均どのぐらい？",
		"option_type": "text",
		"options": [
			{
				"content": "3年",
				"accuracy": 0.524
			},
			{
				"content": "80年",
				"accuracy": 0.253
			}
		],
		"answer": {
			"content": "30年",
			"explanation": ""
		}
	},
	{
		"id": 3,
		"category": "test",
		"content": "「ウナギ」を漢字でどう書く？",
		"option_type": "text",
		"options": [
			{
				"content": "鮭",
				"accuracy": 0.9
			},
			{
				"content": "鮪",
				"accuracy": 0.7
			},
			{
				"content": "鮎",
				"accuracy": 0.6
			},
			{
				"content": "鰯",
				"accuracy": 0.8
			},
			{
				"content": "鯛",
				"accuracy": 0.7
			}
		],
		"answer": {
			"content": "鰻",
			"explanation": ""
		}
	}
]
